{
    "openapi": "3.0.0",
    "info": {
        "title": "Inventory API",
        "description": "Product Inventory Management API",
        "version": "1.0.0"
    },
    "paths": {
        "/api/products": {
            "get": {
                "tags": [
                    "Products"
                ],
                "summary": "Get products list",
                "operationId": "1bfaa78d1c2c3848ab8165c5dadcad3e",
                "responses": {
                    "200": {
                        "description": "Success"
                    }
                }
            }
        }
    },
    "tags": [
        {
            "name": "Products",
            "description": "Products"
        }
    ]
}